silx/__init__.py
silx/__main__.py
silx/_config.py
silx/_utils.py
silx/_version.py
silx/conftest.py
silx/app/__init__.py
silx/app/convert.py
silx/app/test_.py
silx/app/compare/CompareImagesWindow.py
silx/app/compare/__init__.py
silx/app/compare/main.py
silx/app/compare/test/__init__.py
silx/app/compare/test/test_compare.py
silx/app/compare/test/test_launcher.py
silx/app/test/__init__.py
silx/app/test/test_convert.py
silx/app/utils/__init__.py
silx/app/utils/parseutils.py
silx/app/utils/test/__init__.py
silx/app/utils/test/test_parseutils.py
silx/app/view/About.py
silx/app/view/ApplicationContext.py
silx/app/view/CustomNxdataWidget.py
silx/app/view/CustomPlotSelectionWindow.py
silx/app/view/DataPanel.py
silx/app/view/Viewer.py
silx/app/view/__init__.py
silx/app/view/main.py
silx/app/view/test/__init__.py
silx/app/view/test/test_launcher.py
silx/app/view/test/test_plotselection.py
silx/app/view/test/test_view.py
silx/gui/__init__.py
silx/gui/colors.py
silx/gui/conftest.py
silx/gui/console.py
silx/gui/constants.py
silx/gui/icons.py
silx/gui/printer.py
silx/gui/_glutils/Context.py
silx/gui/_glutils/FramebufferTexture.py
silx/gui/_glutils/OpenGLWidget.py
silx/gui/_glutils/Program.py
silx/gui/_glutils/Texture.py
silx/gui/_glutils/VertexBuffer.py
silx/gui/_glutils/__init__.py
silx/gui/_glutils/font.py
silx/gui/_glutils/gl.py
silx/gui/_glutils/utils.py
silx/gui/_glutils/test/__init__.py
silx/gui/_glutils/test/test_gl.py
silx/gui/data/ArrayTableModel.py
silx/gui/data/ArrayTableWidget.py
silx/gui/data/DataViewer.py
silx/gui/data/DataViewerFrame.py
silx/gui/data/DataViewerSelector.py
silx/gui/data/DataViews.py
silx/gui/data/Hdf5TableView.py
silx/gui/data/HexaTableView.py
silx/gui/data/NXdataWidgets.py
silx/gui/data/NumpyAxesSelector.py
silx/gui/data/RecordTableView.py
silx/gui/data/TextFormatter.py
silx/gui/data/_RecordPlot.py
silx/gui/data/_VolumeWindow.py
silx/gui/data/__init__.py
silx/gui/data/test/__init__.py
silx/gui/data/test/test_arraywidget.py
silx-2.2.2.dist-info/licenses/LICENSE
silx-2.2.2.dist-info/METADATA
silx-2.2.2.dist-info/WHEEL
silx-2.2.2.dist-info/entry_points.txt
silx-2.2.2.dist-info/top_level.txt
silx-2.2.2.dist-info/RECORD
