Metadata-Version: 2.4
Name: silx
Version: 2.2.2
Summary: Software library for X-ray data analysis
Home-page: http://www.silx.org/
Author: data analysis unit
Author-email: silx@esrf.fr
License: MIT
Classifier: Development Status :: 5 - Production/Stable
Classifier: Environment :: Console
Classifier: Environment :: MacOS X
Classifier: Environment :: Win32 (MS Windows)
Classifier: Environment :: X11 Applications :: Qt
Classifier: Intended Audience :: Education
Classifier: Intended Audience :: Science/Research
Classifier: License :: OSI Approved :: MIT License
Classifier: Natural Language :: English
Classifier: Operating System :: MacOS
Classifier: Operating System :: Microsoft :: Windows
Classifier: Operating System :: POSIX
Classifier: Programming Language :: Cython
Classifier: Programming Language :: Python :: 3
Classifier: Programming Language :: Python :: Implementation :: CPython
Classifier: Topic :: Scientific/Engineering :: Physics
Classifier: Topic :: Software Development :: Libraries :: Python Modules
Requires-Python: >=3.8
License-File: LICENSE
Requires-Dist: numpy
Requires-Dist: packaging
Requires-Dist: h5py
Requires-Dist: fabio>=0.9
Provides-Extra: full
Requires-Dist: pyopencl; extra == "full"
Requires-Dist: Mako; extra == "full"
Requires-Dist: qtconsole; extra == "full"
Requires-Dist: matplotlib>=3.1.0; extra == "full"
Requires-Dist: PyOpenGL; extra == "full"
Requires-Dist: python-dateutil; extra == "full"
Requires-Dist: PyQt5; extra == "full"
Requires-Dist: hdf5plugin; extra == "full"
Requires-Dist: scipy; extra == "full"
Requires-Dist: Pillow; extra == "full"
Provides-Extra: doc
Requires-Dist: pandoc; extra == "doc"
Requires-Dist: sphinx<8.2; extra == "doc"
Requires-Dist: nbsphinx; extra == "doc"
Requires-Dist: sphinx-autodoc-typehints; extra == "doc"
Requires-Dist: pydata_sphinx_theme; extra == "doc"
Requires-Dist: sphinx-design; extra == "doc"
Requires-Dist: pillow; extra == "doc"
Provides-Extra: test
Requires-Dist: pytest>=6.0; extra == "test"
Requires-Dist: pytest-xvfb; extra == "test"
Requires-Dist: pytest-mock; extra == "test"
Requires-Dist: scipy>=1.10; extra == "test"
Requires-Dist: pooch; extra == "test"
Dynamic: license-file
Dynamic: provides-extra
Dynamic: requires-dist
